irekua_rest_api/__init__.py
irekua_rest_api/apps.py
irekua_rest_api/exception_handler.py
irekua_rest_api/metadata.py
irekua_rest_api/pagination.py
irekua_rest_api/settings.py
irekua_rest_api/version.py
irekua_rest_api/filters/__init__.py
irekua_rest_api/filters/annotation_tools.py
irekua_rest_api/filters/annotation_types.py
irekua_rest_api/filters/annotation_votes.py
irekua_rest_api/filters/annotations.py
irekua_rest_api/filters/collection_administrators.py
irekua_rest_api/filters/collection_devices.py
irekua_rest_api/filters/collection_sites.py
irekua_rest_api/filters/collection_types.py
irekua_rest_api/filters/collection_users.py
irekua_rest_api/filters/data_collections.py
irekua_rest_api/filters/device_brands.py
irekua_rest_api/filters/device_types.py
irekua_rest_api/filters/devices.py
irekua_rest_api/filters/entailment_types.py
irekua_rest_api/filters/entailments.py
irekua_rest_api/filters/event_types.py
irekua_rest_api/filters/institutions.py
irekua_rest_api/filters/item_types.py
irekua_rest_api/filters/items.py
irekua_rest_api/filters/licence_types.py
irekua_rest_api/filters/licences.py
irekua_rest_api/filters/manager_collections.py
irekua_rest_api/filters/metacollections.py
irekua_rest_api/filters/model_predictions.py
irekua_rest_api/filters/model_versions.py
irekua_rest_api/filters/models.py
irekua_rest_api/filters/physical_devices.py
irekua_rest_api/filters/roles.py
irekua_rest_api/filters/sampling_event_devices.py
irekua_rest_api/filters/sampling_event_types.py
irekua_rest_api/filters/sampling_events.py
irekua_rest_api/filters/secondary_items.py
irekua_rest_api/filters/site_types.py
irekua_rest_api/filters/sites.py
irekua_rest_api/filters/synonym_suggestions.py
irekua_rest_api/filters/synonyms.py
irekua_rest_api/filters/tags.py
irekua_rest_api/filters/term_suggestions.py
irekua_rest_api/filters/term_types.py
irekua_rest_api/filters/terms.py
irekua_rest_api/filters/users.py
irekua_rest_api/filters/utils.py
irekua_rest_api/locale/es/LC_MESSAGES/django.mo
irekua_rest_api-0.1.3.dist-info/LICENCE
irekua_rest_api-0.1.3.dist-info/METADATA
irekua_rest_api-0.1.3.dist-info/WHEEL
irekua_rest_api-0.1.3.dist-info/top_level.txt
irekua_rest_api-0.1.3.dist-info/RECORD
