Metadata-Version: 2.1
Name: irekua-rest-api
Version: 0.1.3
Summary: REST API for Irekua access
Home-page: https://github.com/CONABIO-audio/irekua-rest-api
Author: CONABIO, Gustavo Everardo Robredo Esquivelzeta, Santiago Martínez Balvanera
Author-email: erobredo@conabio.gob.mx, smartinez@conabio.gob.mx
License: BSD License
Platform: UNKNOWN
Classifier: Environment :: Web Environment
Classifier: Framework :: Django
Classifier: Framework :: Django :: 3.0
Classifier: Intended Audience :: Developers
Classifier: License :: OSI Approved :: BSD License
Classifier: Operating System :: OS Independent
Classifier: Programming Language :: Python
Classifier: Programming Language :: Python :: 3.5
Classifier: Programming Language :: Python :: 3.6
Classifier: Programming Language :: Python :: 3.7
Classifier: Topic :: Internet :: WWW/HTTP
Classifier: Topic :: Internet :: WWW/HTTP :: Dynamic Content
Requires-Dist: irekua-database
Requires-Dist: irekua-models
Requires-Dist: irekua-filters
Requires-Dist: irekua-permissions
Requires-Dist: djangorestframework
Requires-Dist: markdown
Requires-Dist: django-filter
Requires-Dist: coreapi
Requires-Dist: pyyaml
